uw_grad/VERSION
uw_grad/__init__.py
uw_grad/committee.py
uw_grad/dao.py
uw_grad/degree.py
uw_grad/leave.py
uw_grad/models.py
uw_grad/petition.py
uw_grad/test.py
uw_grad/util.py
uw_grad/resources/grad/file/services/students/v1/api/committee_id_000083856_status_active
uw_grad/resources/grad/file/services/students/v1/api/leave_id_000083856
uw_grad/resources/grad/file/services/students/v1/api/petition_id_000083856
uw_grad/resources/grad/file/services/students/v1/api/request_id_000083856_exclude_past_quarter_true
uw_grad/tests/__init__.py
uw_grad/tests/test_committee.py
uw_grad/tests/test_degree.py
uw_grad/tests/test_leave.py
uw_grad/tests/test_petition.py
uw_restclients_grad-1.1.3.dist-info/licenses/LICENSE
uw_restclients_grad-1.1.3.dist-info/METADATA
uw_restclients_grad-1.1.3.dist-info/WHEEL
uw_restclients_grad-1.1.3.dist-info/top_level.txt
uw_restclients_grad-1.1.3.dist-info/RECORD
