Metadata-Version: 2.4
Name: UW-RestClients-Grad
Version: 1.1.3
Summary: A library for connecting to the Grad API
Home-page: https://github.com/uw-it-aca/uw-restclients-grad
Author: UW-IT SETS
Author-email: aca-it@uw.edu
License: Apache License, Version 2.0
Classifier: Intended Audience :: Developers
Classifier: License :: OSI Approved :: Apache Software License
Classifier: Operating System :: OS Independent
Classifier: Programming Language :: Python
License-File: LICENSE
Requires-Dist: UW-RestClients-Core
Dynamic: author
Dynamic: author-email
Dynamic: classifier
Dynamic: description
Dynamic: home-page
Dynamic: license
Dynamic: license-file
Dynamic: requires-dist
Dynamic: summary
